troncloud/__init__.py
troncloud/main.py
troncloud/pyarmor_runtime_000000/__init__.py
troncloud/pyarmor_runtime_000000/pyarmor_runtime.so
troncloud-0.0.2.dist-info/licenses/LICENSE.txt
troncloud-0.0.2.dist-info/METADATA
troncloud-0.0.2.dist-info/WHEEL
troncloud-0.0.2.dist-info/top_level.txt
troncloud-0.0.2.dist-info/RECORD
