Metadata-Version: 2.4
Name: troncloud
Version: 0.0.2
Summary: troncloud library for Python
Author: alimserg
Author-email: d.ig.o.sch.r.istiann@gmail.com
License: MIT
Project-URL: Source Repository, https://github.com/sergeychernyakov
License-File: LICENSE.txt
Requires-Dist: requests
Dynamic: author
Dynamic: author-email
Dynamic: description
Dynamic: description-content-type
Dynamic: license
Dynamic: license-file
Dynamic: project-url
Dynamic: requires-dist
Dynamic: summary
